{"routes": [{"destination": {"icao": "FAOR", "iata": "JNB", "name": "Jo'anna OR Tambo", "shortName": "OR Tambo", "municipalityName": "Jo'anna", "location": {"lat": -26.1392, "lon": 28.246}, "countryCode": "ZA"}, "averageDailyFlights": 4.43, "operators": [{"name": "South African Airlink", "iata": "4Z", "icao": "LNK"}, {"name": "CemAir", "iata": "5Z", "icao": "KEM"}]}, {"destination": {"icao": "FACT", "iata": "CPT", "name": "Cape Town ", "shortName": "Cape Town", "municipalityName": "Cape Town", "location": {"lat": -33.9648, "lon": 18.6017}, "countryCode": "ZA"}, "averageDailyFlights": 2.43, "operators": [{"name": "South African Airlink", "iata": "4Z", "icao": "LNK"}, {"name": "CemAir", "iata": "5Z", "icao": "KEM"}]}]}