{"routes": [{"destination": {"icao": "KABQ", "iata": "ABQ", "name": "The Duke City Albuquerque  Sunport", "shortName": "Albuquerque  Sunport", "municipalityName": "The Duke City", "location": {"lat": 35.0402, "lon": -106.609}, "countryCode": "US"}, "averageDailyFlights": 1.86, "operators": [{"name": "Advanced Air", "iata": "AN", "icao": "WSN"}]}, {"destination": {"icao": "KPHX", "iata": "PHX", "name": "Phoenix Sky Harbor", "shortName": "Sky Harbor", "municipalityName": "Phoenix", "location": {"lat": 33.4343, "lon": -112.012}, "countryCode": "US"}, "averageDailyFlights": 1.14, "operators": [{"name": "Advanced Air", "iata": "AN", "icao": "WSN"}]}]}