{"routes": [{"destination": {"name": "Su-Lukaut"}, "averageDailyFlights": 7.57, "operators": [{"name": "Bearskin Airlines", "iata": "JV", "icao": "BLS"}, {"name": "Air Antwerp", "iata": "WP", "icao": "ATW"}]}, {"destination": {"icao": "CYQT", "iata": "YQT", "name": "Thunder Bay ", "shortName": "Thunder Bay", "municipalityName": "Thunder Bay", "location": {"lat": 48.3719, "lon": -89.3239}, "countryCode": "CA"}, "averageDailyFlights": 6.29, "operators": [{"name": "Bearskin Airlines", "iata": "JV", "icao": "BLS"}, {"name": "Air Antwerp", "iata": "WP", "icao": "ATW"}]}, {"destination": {"icao": "CYRL", "iata": "YRL", "name": "Red Lake ", "shortName": "Red Lake", "municipalityName": "Red Lake", "location": {"lat": 51.0669, "lon": -93.7931}, "countryCode": "CA"}, "averageDailyFlights": 4.0, "operators": [{"name": "Bearskin Airlines", "iata": "JV", "icao": "BLS"}, {"name": "Air Antwerp", "iata": "WP", "icao": "ATW"}]}, {"destination": {"name": "Fort-Severn"}, "averageDailyFlights": 1.0, "operators": [{"name": "Air Antwerp", "iata": "WP", "icao": "ATW"}]}, {"destination": {"icao": "CYPM", "iata": "YPM", "name": "Pikangikum ", "shortName": "Pikangikum", "municipalityName": "Pikangikum", "location": {"lat": 51.8197, "lon": -93.9733}, "countryCode": "CA"}, "averageDailyFlights": 0.71, "operators": [{"name": "Bearskin Airlines", "iata": "JV", "icao": "BLS"}]}, {"destination": {"name": "Big-Traut"}, "averageDailyFlights": 0.71, "operators": [{"name": "Air Antwerp", "iata": "WP", "icao": "ATW"}]}, {"destination": {"icao": "CKQ3", "iata": "YNO", "name": "North Spirit Lake ", "shortName": "North Spirit Lake", "municipalityName": "North Spirit Lake", "location": {"lat": 52.49, "lon": -92.9711}, "countryCode": "CA"}, "averageDailyFlights": 0.57, "operators": [{"name": "Bearskin Airlines", "iata": "JV", "icao": "BLS"}]}]}