[
    {
        "movement": {
            "airport": {
                "icao": "WIDD",
                "iata": "BTH",
                "name": "Batam Island",
                "timeZone": "Asia/Jakarta"
            },
            "scheduledTime": {
                "utc": "2024-04-01 01:55Z",
                "local": "2024-04-01 08:55+07:00"
            }
        },
        "aircraft": {
            "model": "Boeing 737-900"
        },
        "airline": {
            "name": "Lion Air",
            "iata": "JT",
            "icao": "LNI"
        }
    },
    {
        "movement": {
            "airport": {
                "icao": "WIII",
                "iata": "CGK",
                "name": "Jakarta",
                "timeZone": "Asia/Jakarta"
            },
            "scheduledTime": {
                "utc": "2024-04-01 03:00Z",
                "local": "2024-04-01 10:00+07:00"
            }
        },
        "aircraft": {
            "model": "Airbus A320"
        },
        "airline": {
            "name": "Super Air Jet",
            "iata": "IU",
            "icao": "SJV"
        }
    },
    {
        "movement": {
            "airport": {
                "icao": "WIMM",
                "iata": "KNO",
                "name": "Medan",
                "timeZone": "Asia/Jakarta"
            },
            "scheduledTime": {
                "utc": "2024-04-01 03:20Z",
                "local": "2024-04-01 10:20+07:00"
            }
        },
        "aircraft": {
            "model": "Airbus A320"
        },
        "airline": {
            "name": "Super Air Jet",
            "iata": "IU",
            "icao": "SJV"
        }
    },
    {
        "movement": {
            "airport": {
                "icao": "WIDD",
                "iata": "BTH",
                "name": "Batam Island",
                "timeZone": "Asia/Jakarta"
            },
            "scheduledTime": {
                "utc": "2024-04-01 04:30Z",
                "local": "2024-04-01 11:30+07:00"
            }
        },
        "aircraft": {
            "model": "Boeing 737-800"
        },
        "airline": {
            "name": "Lion Air",
            "iata": "JT",
            "icao": "LNI"
        }
    },
    {
        "movement": {
            "airport": {
                "icao": "WMKK",
                "iata": "KUL",
                "name": "Kuala Lumpur",
                "timeZone": "Asia/Kuala_Lumpur"
            },
            "scheduledTime": {
                "utc": "2024-04-01 01:25Z",
                "local": "2024-04-01 08:25+07:00"
            }
        },
        "aircraft": {
            "model": "Airbus A320 NEO"
        },
        "airline": {
            "name": "AirAsia",
            "iata": "AK",
            "icao": "AXM"
        }
    },
    {
        "movement": {
            "airport": {
                "icao": "WIII",
                "iata": "CGK",
                "name": "Jakarta",
                "timeZone": "Asia/Jakarta"
            },
            "scheduledTime": {
                "utc": "2024-04-01 01:00Z",
                "local": "2024-04-01 08:00+07:00"
            }
        },
        "aircraft": {
            "model": "Boeing 737-800"
        },
        "airline": {
            "name": "Garuda Indonesia",
            "iata": "GA",
            "icao": "GIA"
        }
    },
    {
        "movement": {
            "airport": {
                "icao": "WIII",
                "iata": "CGK",
                "name": "Jakarta",
                "timeZone": "Asia/Jakarta"
            },
            "scheduledTime": {
                "utc": "2024-04-01 00:05Z",
                "local": "2024-04-01 07:05+07:00"
            }
        },
        "aircraft": {
            "model": "Airbus A320"
        },
        "airline": {
            "name": "Super Air Jet",
            "iata": "IU",
            "icao": "SJV"
        }
    },
    {
        "movement": {
            "airport": {
                "icao": "WIDD",
                "iata": "BTH",
                "name": "Batam Island",
                "timeZone": "Asia/Jakarta"
            },
            "scheduledTime": {
                "utc": "2024-04-01 00:00Z",
                "local": "2024-04-01 07:00+07:00"
            }
        },
        "aircraft": {
            "model": "Airbus A320"
        },
        "airline": {
            "name": "Super Air Jet",
            "iata": "IU",
            "icao": "SJV"
        }
    },
    {
        "movement": {
            "airport": {
                "icao": "WIDD",
                "iata": "BTH",
                "name": "Batam Island",
                "timeZone": "Asia/Jakarta"
            },
            "scheduledTime": {
                "utc": "2024-04-01 02:20Z",
                "local": "2024-04-01 09:20+07:00"
            }
        },
        "aircraft": {
            "model": "Airbus A320"
        },
        "airline": {
            "name": "Citilink",
            "iata": "QG",
            "icao": "CTV"
        }
    },
    {
        "movement": {
            "airport": {
                "icao": "WIII",
                "iata": "CGK",
                "name": "Jakarta",
                "timeZone": "Asia/Jakarta"
            },
            "scheduledTime": {
                "utc": "2024-04-01 02:25Z",
                "local": "2024-04-01 09:25+07:00"
            }
        },
        "aircraft": {
            "model": "Airbus A320"
        },
        "airline": {
            "name": "Citilink",
            "iata": "QG",
            "icao": "CTV"
        }
    },
    {
        "movement": {
            "airport": {
                "icao": "WIII",
                "iata": "CGK",
                "name": "Jakarta",
                "timeZone": "Asia/Jakarta"
            },
            "scheduledTime": {
                "utc": "2024-04-01 05:00Z",
                "local": "2024-04-01 12:00+07:00"
            }
        },
        "aircraft": {
            "model": "Boeing 737-800"
        },
        "airline": {
            "name": "Garuda Indonesia",
            "iata": "GA",
            "icao": "GIA"
        }
    },
    {
        "movement": {
            "airport": {
                "icao": "WMKK",
                "iata": "KUL",
                "name": "Kuala Lumpur",
                "timeZone": "Asia/Kuala_Lumpur"
            },
            "scheduledTime": {
                "utc": "2024-04-01 06:40Z",
                "local": "2024-04-01 13:40+07:00"
            }
        },
        "aircraft": {
            "model": "Airbus A320"
        },
        "airline": {
            "name": "Super Air Jet",
            "iata": "IU",
            "icao": "SJV"
        }
    },
    {
        "movement": {
            "airport": {
                "icao": "WIII",
                "iata": "CGK",
                "name": "Jakarta",
                "timeZone": "Asia/Jakarta"
            },
            "scheduledTime": {
                "utc": "2024-04-01 07:20Z",
                "local": "2024-04-01 14:20+07:00"
            }
        },
        "aircraft": {
            "model": "Airbus A320"
        },
        "airline": {
            "name": "Citilink",
            "iata": "QG",
            "icao": "CTV"
        }
    },
    {
        "movement": {
            "airport": {
                "icao": "WIII",
                "iata": "CGK",
                "name": "Jakarta",
                "timeZone": "Asia/Jakarta"
            },
            "scheduledTime": {
                "utc": "2024-04-01 08:00Z",
                "local": "2024-04-01 15:00+07:00"
            }
        },
        "aircraft": {
            "model": "Airbus A320"
        },
        "airline": {
            "name": "Super Air Jet",
            "iata": "IU",
            "icao": "SJV"
        }
    },
    {
        "movement": {
            "airport": {
                "icao": "WMKK",
                "iata": "KUL",
                "name": "Kuala Lumpur",
                "timeZone": "Asia/Kuala_Lumpur"
            },
            "scheduledTime": {
                "utc": "2024-04-01 09:05Z",
                "local": "2024-04-01 16:05+07:00"
            }
        },
        "aircraft": {
            "model": "Airbus A320"
        },
        "airline": {
            "name": "AirAsia",
            "iata": "AK",
            "icao": "AXM"
        }
    },
    {
        "movement": {
            "airport": {
                "icao": "WIDD",
                "iata": "BTH",
                "name": "Batam Island",
                "timeZone": "Asia/Jakarta"
            },
            "scheduledTime": {
                "utc": "2024-04-01 09:10Z",
                "local": "2024-04-01 16:10+07:00"
            }
        },
        "aircraft": {
            "model": "Boeing 737-900"
        },
        "airline": {
            "name": "Lion Air",
            "iata": "JT",
            "icao": "LNI"
        }
    },
    {
        "movement": {
            "airport": {
                "icao": "WIII",
                "iata": "CGK",
                "name": "Jakarta",
                "timeZone": "Asia/Jakarta"
            },
            "scheduledTime": {
                "utc": "2024-04-01 09:30Z",
                "local": "2024-04-01 16:30+07:00"
            }
        },
        "aircraft": {
            "model": "Boeing 737-800"
        },
        "airline": {
            "name": "Garuda Indonesia",
            "iata": "GA",
            "icao": "GIA"
        }
    },
    {
        "movement": {
            "airport": {
                "icao": "WIII",
                "iata": "CGK",
                "name": "Jakarta",
                "timeZone": "Asia/Jakarta"
            },
            "scheduledTime": {
                "utc": "2024-04-01 09:35Z",
                "local": "2024-04-01 16:35+07:00"
            }
        },
        "aircraft": {
            "model": "Airbus A320"
        },
        "airline": {
            "name": "Super Air Jet",
            "iata": "IU",
            "icao": "SJV"
        }
    },
    {
        "movement": {
            "airport": {
                "icao": "WIII",
                "iata": "CGK",
                "name": "Jakarta",
                "timeZone": "Asia/Jakarta"
            },
            "scheduledTime": {
                "utc": "2024-04-01 10:50Z",
                "local": "2024-04-01 17:50+07:00"
            }
        },
        "aircraft": {
            "model": "Airbus A320"
        },
        "airline": {
            "name": "Citilink",
            "iata": "QG",
            "icao": "CTV"
        }
    },
    {
        "movement": {
            "airport": {
                "icao": "WIII",
                "iata": "CGK",
                "name": "Jakarta",
                "timeZone": "Asia/Jakarta"
            },
            "scheduledTime": {
                "utc": "2024-04-01 11:30Z",
                "local": "2024-04-01 18:30+07:00"
            }
        },
        "aircraft": {
            "model": "Airbus A320"
        },
        "airline": {
            "name": "Super Air Jet",
            "iata": "IU",
            "icao": "SJV"
        }
    },
    {
        "movement": {
            "airport": {
                "icao": "WIII",
                "iata": "CGK",
                "name": "Jakarta",
                "timeZone": "Asia/Jakarta"
            },
            "scheduledTime": {
                "utc": "2024-04-01 12:10Z",
                "local": "2024-04-01 19:10+07:00"
            }
        },
        "aircraft": {
            "model": "Airbus A320"
        },
        "airline": {
            "name": "Citilink",
            "iata": "QG",
            "icao": "CTV"
        }
    },
    {
        "movement": {
            "airport": {
                "icao": "WIDD",
                "iata": "BTH",
                "name": "Batam Island",
                "timeZone": "Asia/Jakarta"
            },
            "scheduledTime": {
                "utc": "2024-04-01 12:15Z",
                "local": "2024-04-01 19:15+07:00"
            }
        },
        "aircraft": {
            "model": "Airbus A320"
        },
        "airline": {
            "name": "Citilink",
            "iata": "QG",
            "icao": "CTV"
        }
    },
    {
        "movement": {
            "airport": {
                "icao": "WIDD",
                "iata": "BTH",
                "name": "Batam Island",
                "timeZone": "Asia/Jakarta"
            },
            "scheduledTime": {
                "utc": "2024-04-01 12:55Z",
                "local": "2024-04-01 19:55+07:00"
            }
        },
        "aircraft": {
            "model": "Boeing 737-800"
        },
        "airline": {
            "name": "Lion Air",
            "iata": "JT",
            "icao": "LNI"
        }
    },
    {
        "movement": {
            "airport": {
                "icao": "WIHH",
                "iata": "HLP",
                "name": "Jakarta",
                "timeZone": "Asia/Jakarta"
            },
            "scheduledTime": {
                "utc": "2024-04-01 06:10Z",
                "local": "2024-04-01 13:10+07:00"
            }
        },
        "aircraft": {
            "model": "Airbus A320"
        },
        "airline": {
            "name": "Citilink",
            "iata": "QG",
            "icao": "CTV"
        }
    },
    {
        "movement": {
            "airport": {
                "icao": "WIII",
                "iata": "CGK",
                "name": "Jakarta",
                "timeZone": "Asia/Jakarta"
            },
            "scheduledTime": {
                "utc": "2024-04-01 06:15Z",
                "local": "2024-04-01 13:15+07:00"
            }
        },
        "aircraft": {
            "model": "Airbus A320"
        },
        "airline": {
            "name": "Super Air Jet",
            "iata": "IU",
            "icao": "SJV"
        }
    },
    {
        "movement": {
            "airport": {
                "icao": "WIII",
                "iata": "CGK",
                "name": "Jakarta",
                "timeZone": "Asia/Jakarta"
            },
            "scheduledTime": {
                "utc": "2024-04-02 02:25Z",
                "local": "2024-04-02 09:25+07:00"
            }
        },
        "aircraft": {
            "model": "Airbus A320"
        },
        "airline": {
            "name": "Citilink",
            "iata": "QG",
            "icao": "CTV"
        }
    },
    {
        "movement": {
            "airport": {
                "icao": "WIII",
                "iata": "CGK",
                "name": "Jakarta",
                "timeZone": "Asia/Jakarta"
            },
            "scheduledTime": {
                "utc": "2024-04-02 03:00Z",
                "local": "2024-04-02 10:00+07:00"
            }
        },
        "aircraft": {
            "model": "Airbus A320"
        },
        "airline": {
            "name": "Super Air Jet",
            "iata": "IU",
            "icao": "SJV"
        }
    },
    {
        "movement": {
            "airport": {
                "icao": "WIMM",
                "iata": "KNO",
                "name": "Medan",
                "timeZone": "Asia/Jakarta"
            },
            "scheduledTime": {
                "utc": "2024-04-02 03:20Z",
                "local": "2024-04-02 10:20+07:00"
            }
        },
        "aircraft": {
            "model": "Airbus A320"
        },
        "airline": {
            "name": "Super Air Jet",
            "iata": "IU",
            "icao": "SJV"
        }
    },
    {
        "movement": {
            "airport": {
                "icao": "WIDD",
                "iata": "BTH",
                "name": "Batam Island",
                "timeZone": "Asia/Jakarta"
            },
            "scheduledTime": {
                "utc": "2024-04-02 04:30Z",
                "local": "2024-04-02 11:30+07:00"
            }
        },
        "aircraft": {
            "model": "Boeing 737-800"
        },
        "airline": {
            "name": "Lion Air",
            "iata": "JT",
            "icao": "LNI"
        }
    },
    {
        "movement": {
            "airport": {
                "icao": "WMKK",
                "iata": "KUL",
                "name": "Kuala Lumpur",
                "timeZone": "Asia/Kuala_Lumpur"
            },
            "scheduledTime": {
                "utc": "2024-04-02 04:35Z",
                "local": "2024-04-02 11:35+07:00"
            }
        },
        "aircraft": {
            "model": "Airbus A320"
        },
        "airline": {
            "name": "AirAsia",
            "iata": "AK",
            "icao": "AXM"
        }
    },
    {
        "movement": {
            "airport": {
                "icao": "WIDD",
                "iata": "BTH",
                "name": "Batam Island",
                "timeZone": "Asia/Jakarta"
            },
            "scheduledTime": {
                "utc": "2024-04-02 01:55Z",
                "local": "2024-04-02 08:55+07:00"
            }
        },
        "aircraft": {
            "model": "Boeing 737-900"
        },
        "airline": {
            "name": "Lion Air",
            "iata": "JT",
            "icao": "LNI"
        }
    },
    {
        "movement": {
            "airport": {
                "icao": "WMKK",
                "iata": "KUL",
                "name": "Kuala Lumpur",
                "timeZone": "Asia/Kuala_Lumpur"
            },
            "scheduledTime": {
                "utc": "2024-04-02 01:25Z",
                "local": "2024-04-02 08:25+07:00"
            }
        },
        "aircraft": {
            "model": "Airbus A320 NEO"
        },
        "airline": {
            "name": "AirAsia",
            "iata": "AK",
            "icao": "AXM"
        }
    },
    {
        "movement": {
            "airport": {
                "icao": "WIII",
                "iata": "CGK",
                "name": "Jakarta",
                "timeZone": "Asia/Jakarta"
            },
            "scheduledTime": {
                "utc": "2024-04-02 01:00Z",
                "local": "2024-04-02 08:00+07:00"
            }
        },
        "aircraft": {
            "model": "Boeing 737-800"
        },
        "airline": {
            "name": "Garuda Indonesia",
            "iata": "GA",
            "icao": "GIA"
        }
    },
    {
        "movement": {
            "airport": {
                "icao": "WIII",
                "iata": "CGK",
                "name": "Jakarta",
                "timeZone": "Asia/Jakarta"
            },
            "scheduledTime": {
                "utc": "2024-04-02 00:05Z",
                "local": "2024-04-02 07:05+07:00"
            }
        },
        "aircraft": {
            "model": "Airbus A320"
        },
        "airline": {
            "name": "Super Air Jet",
            "iata": "IU",
            "icao": "SJV"
        }
    },
    {
        "movement": {
            "airport": {
                "icao": "WIDD",
                "iata": "BTH",
                "name": "Batam Island",
                "timeZone": "Asia/Jakarta"
            },
            "scheduledTime": {
                "utc": "2024-04-02 00:00Z",
                "local": "2024-04-02 07:00+07:00"
            }
        },
        "aircraft": {
            "model": "Airbus A320"
        },
        "airline": {
            "name": "Super Air Jet",
            "iata": "IU",
            "icao": "SJV"
        }
    },
    {
        "movement": {
            "airport": {
                "icao": "WIII",
                "iata": "CGK",
                "name": "Jakarta",
                "timeZone": "Asia/Jakarta"
            },
            "scheduledTime": {
                "utc": "2024-04-02 05:00Z",
                "local": "2024-04-02 12:00+07:00"
            }
        },
        "aircraft": {
            "model": "Boeing 737-800"
        },
        "airline": {
            "name": "Garuda Indonesia",
            "iata": "GA",
            "icao": "GIA"
        }
    },
    {
        "movement": {
            "airport": {
                "icao": "WIDD",
                "iata": "BTH",
                "name": "Batam Island",
                "timeZone": "Asia/Jakarta"
            },
            "scheduledTime": {
                "utc": "2024-04-02 05:15Z",
                "local": "2024-04-02 12:15+07:00"
            }
        },
        "aircraft": {
            "model": "Airbus A320"
        },
        "airline": {
            "name": "Citilink",
            "iata": "QG",
            "icao": "CTV"
        }
    },
    {
        "movement": {
            "airport": {
                "icao": "WIHH",
                "iata": "HLP",
                "name": "Jakarta",
                "timeZone": "Asia/Jakarta"
            },
            "scheduledTime": {
                "utc": "2024-04-02 06:10Z",
                "local": "2024-04-02 13:10+07:00"
            }
        },
        "aircraft": {
            "model": "Airbus A320"
        },
        "airline": {
            "name": "Citilink",
            "iata": "QG",
            "icao": "CTV"
        }
    },
    {
        "movement": {
            "airport": {
                "icao": "WIII",
                "iata": "CGK",
                "name": "Jakarta",
                "timeZone": "Asia/Jakarta"
            },
            "scheduledTime": {
                "utc": "2024-04-02 06:15Z",
                "local": "2024-04-02 13:15+07:00"
            }
        },
        "aircraft": {
            "model": "Airbus A320"
        },
        "airline": {
            "name": "Super Air Jet",
            "iata": "IU",
            "icao": "SJV"
        }
    },
    {
        "movement": {
            "airport": {
                "icao": "WMKK",
                "iata": "KUL",
                "name": "Kuala Lumpur",
                "timeZone": "Asia/Kuala_Lumpur"
            },
            "scheduledTime": {
                "utc": "2024-04-02 06:40Z",
                "local": "2024-04-02 13:40+07:00"
            }
        },
        "aircraft": {
            "model": "Airbus A320"
        },
        "airline": {
            "name": "Super Air Jet",
            "iata": "IU",
            "icao": "SJV"
        }
    },
    {
        "movement": {
            "airport": {
                "icao": "WIII",
                "iata": "CGK",
                "name": "Jakarta",
                "timeZone": "Asia/Jakarta"
            },
            "scheduledTime": {
                "utc": "2024-04-02 08:00Z",
                "local": "2024-04-02 15:00+07:00"
            }
        },
        "aircraft": {
            "model": "Airbus A320"
        },
        "airline": {
            "name": "Super Air Jet",
            "iata": "IU",
            "icao": "SJV"
        }
    },
    {
        "movement": {
            "airport": {
                "icao": "WIDD",
                "iata": "BTH",
                "name": "Batam Island",
                "timeZone": "Asia/Jakarta"
            },
            "scheduledTime": {
                "utc": "2024-04-02 09:10Z",
                "local": "2024-04-02 16:10+07:00"
            }
        },
        "aircraft": {
            "model": "Boeing 737-900"
        },
        "airline": {
            "name": "Lion Air",
            "iata": "JT",
            "icao": "LNI"
        }
    },
    {
        "movement": {
            "airport": {
                "icao": "WIII",
                "iata": "CGK",
                "name": "Jakarta",
                "timeZone": "Asia/Jakarta"
            },
            "scheduledTime": {
                "utc": "2024-04-02 09:30Z",
                "local": "2024-04-02 16:30+07:00"
            }
        },
        "aircraft": {
            "model": "Boeing 737-800"
        },
        "airline": {
            "name": "Garuda Indonesia",
            "iata": "GA",
            "icao": "GIA"
        }
    },
    {
        "movement": {
            "airport": {
                "icao": "WIII",
                "iata": "CGK",
                "name": "Jakarta",
                "timeZone": "Asia/Jakarta"
            },
            "scheduledTime": {
                "utc": "2024-04-02 09:35Z",
                "local": "2024-04-02 16:35+07:00"
            }
        },
        "aircraft": {
            "model": "Airbus A320"
        },
        "airline": {
            "name": "Super Air Jet",
            "iata": "IU",
            "icao": "SJV"
        }
    },
    {
        "movement": {
            "airport": {
                "icao": "WIII",
                "iata": "CGK",
                "name": "Jakarta",
                "timeZone": "Asia/Jakarta"
            },
            "scheduledTime": {
                "utc": "2024-04-02 11:30Z",
                "local": "2024-04-02 18:30+07:00"
            }
        },
        "aircraft": {
            "model": "Airbus A320"
        },
        "airline": {
            "name": "Super Air Jet",
            "iata": "IU",
            "icao": "SJV"
        }
    },
    {
        "movement": {
            "airport": {
                "icao": "WIDD",
                "iata": "BTH",
                "name": "Batam Island",
                "timeZone": "Asia/Jakarta"
            },
            "scheduledTime": {
                "utc": "2024-04-02 12:15Z",
                "local": "2024-04-02 19:15+07:00"
            }
        },
        "aircraft": {
            "model": "Airbus A320"
        },
        "airline": {
            "name": "Citilink",
            "iata": "QG",
            "icao": "CTV"
        }
    },
    {
        "movement": {
            "airport": {
                "icao": "WIDD",
                "iata": "BTH",
                "name": "Batam Island",
                "timeZone": "Asia/Jakarta"
            },
            "scheduledTime": {
                "utc": "2024-04-02 12:55Z",
                "local": "2024-04-02 19:55+07:00"
            }
        },
        "aircraft": {
            "model": "Boeing 737-800"
        },
        "airline": {
            "name": "Lion Air",
            "iata": "JT",
            "icao": "LNI"
        }
    },
    {
        "movement": {
            "airport": {
                "icao": "WIII",
                "iata": "CGK",
                "name": "Jakarta",
                "timeZone": "Asia/Jakarta"
            },
            "scheduledTime": {
                "utc": "2024-04-02 07:20Z",
                "local": "2024-04-02 14:20+07:00"
            }
        },
        "aircraft": {
            "model": "Airbus A320"
        },
        "airline": {
            "name": "Citilink",
            "iata": "QG",
            "icao": "CTV"
        }
    },
    {
        "movement": {
            "airport": {
                "icao": "WIII",
                "iata": "CGK",
                "name": "Jakarta",
                "timeZone": "Asia/Jakarta"
            },
            "scheduledTime": {
                "utc": "2024-04-02 10:50Z",
                "local": "2024-04-02 17:50+07:00"
            }
        },
        "aircraft": {
            "model": "Airbus A320"
        },
        "airline": {
            "name": "Citilink",
            "iata": "QG",
            "icao": "CTV"
        }
    },
    {
        "movement": {
            "airport": {
                "icao": "WIDD",
                "iata": "BTH",
                "name": "Batam Island",
                "timeZone": "Asia/Jakarta"
            },
            "scheduledTime": {
                "utc": "2024-04-03 00:00Z",
                "local": "2024-04-03 07:00+07:00"
            }
        },
        "aircraft": {
            "model": "Airbus A320"
        },
        "airline": {
            "name": "Super Air Jet",
            "iata": "IU",
            "icao": "SJV"
        }
    },
    {
        "movement": {
            "airport": {
                "icao": "WIII",
                "iata": "CGK",
                "name": "Jakarta",
                "timeZone": "Asia/Jakarta"
            },
            "scheduledTime": {
                "utc": "2024-04-03 00:05Z",
                "local": "2024-04-03 07:05+07:00"
            }
        },
        "aircraft": {
            "model": "Airbus A320"
        },
        "airline": {
            "name": "Super Air Jet",
            "iata": "IU",
            "icao": "SJV"
        }
    },
    {
        "movement": {
            "airport": {
                "icao": "WIII",
                "iata": "CGK",
                "name": "Jakarta",
                "timeZone": "Asia/Jakarta"
            },
            "scheduledTime": {
                "utc": "2024-04-03 01:00Z",
                "local": "2024-04-03 08:00+07:00"
            }
        },
        "aircraft": {
            "model": "Boeing 737-800"
        },
        "airline": {
            "name": "Garuda Indonesia",
            "iata": "GA",
            "icao": "GIA"
        }
    },
    {
        "movement": {
            "airport": {
                "icao": "WMKK",
                "iata": "KUL",
                "name": "Kuala Lumpur",
                "timeZone": "Asia/Kuala_Lumpur"
            },
            "scheduledTime": {
                "utc": "2024-04-03 01:25Z",
                "local": "2024-04-03 08:25+07:00"
            }
        },
        "aircraft": {
            "model": "Airbus A320"
        },
        "airline": {
            "name": "AirAsia",
            "iata": "AK",
            "icao": "AXM"
        }
    },
    {
        "movement": {
            "airport": {
                "icao": "WIDD",
                "iata": "BTH",
                "name": "Batam Island",
                "timeZone": "Asia/Jakarta"
            },
            "scheduledTime": {
                "utc": "2024-04-03 01:55Z",
                "local": "2024-04-03 08:55+07:00"
            }
        },
        "aircraft": {
            "model": "Boeing 737-900"
        },
        "airline": {
            "name": "Lion Air",
            "iata": "JT",
            "icao": "LNI"
        }
    },
    {
        "movement": {
            "airport": {
                "icao": "WIII",
                "iata": "CGK",
                "name": "Jakarta",
                "timeZone": "Asia/Jakarta"
            },
            "scheduledTime": {
                "utc": "2024-04-03 02:25Z",
                "local": "2024-04-03 09:25+07:00"
            }
        },
        "aircraft": {
            "model": "Airbus A320"
        },
        "airline": {
            "name": "Citilink",
            "iata": "QG",
            "icao": "CTV"
        }
    },
    {
        "movement": {
            "airport": {
                "icao": "WIII",
                "iata": "CGK",
                "name": "Jakarta",
                "timeZone": "Asia/Jakarta"
            },
            "scheduledTime": {
                "utc": "2024-04-03 03:00Z",
                "local": "2024-04-03 10:00+07:00"
            }
        },
        "aircraft": {
            "model": "Airbus A320"
        },
        "airline": {
            "name": "Super Air Jet",
            "iata": "IU",
            "icao": "SJV"
        }
    },
    {
        "movement": {
            "airport": {
                "icao": "WIMM",
                "iata": "KNO",
                "name": "Medan",
                "timeZone": "Asia/Jakarta"
            },
            "scheduledTime": {
                "utc": "2024-04-03 03:20Z",
                "local": "2024-04-03 10:20+07:00"
            }
        },
        "aircraft": {
            "model": "Airbus A320"
        },
        "airline": {
            "name": "Super Air Jet",
            "iata": "IU",
            "icao": "SJV"
        }
    },
    {
        "movement": {
            "airport": {
                "icao": "WIDD",
                "iata": "BTH",
                "name": "Batam Island",
                "timeZone": "Asia/Jakarta"
            },
            "scheduledTime": {
                "utc": "2024-04-03 03:40Z",
                "local": "2024-04-03 10:40+07:00"
            }
        },
        "aircraft": {
            "model": "Airbus A320"
        },
        "airline": {
            "name": "Super Air Jet",
            "iata": "IU",
            "icao": "SJV"
        }
    },
    {
        "movement": {
            "airport": {
                "icao": "WIDD",
                "iata": "BTH",
                "name": "Batam Island",
                "timeZone": "Asia/Jakarta"
            },
            "scheduledTime": {
                "utc": "2024-04-03 04:30Z",
                "local": "2024-04-03 11:30+07:00"
            }
        },
        "aircraft": {
            "model": "Boeing 737-800"
        },
        "airline": {
            "name": "Lion Air",
            "iata": "JT",
            "icao": "LNI"
        }
    },
    {
        "movement": {
            "airport": {
                "icao": "WMKK",
                "iata": "KUL",
                "name": "Kuala Lumpur",
                "timeZone": "Asia/Kuala_Lumpur"
            },
            "scheduledTime": {
                "utc": "2024-04-03 04:35Z",
                "local": "2024-04-03 11:35+07:00"
            }
        },
        "aircraft": {
            "model": "Airbus A320"
        },
        "airline": {
            "name": "AirAsia",
            "iata": "AK",
            "icao": "AXM"
        }
    },
    {
        "movement": {
            "airport": {
                "icao": "WIII",
                "iata": "CGK",
                "name": "Jakarta",
                "timeZone": "Asia/Jakarta"
            },
            "scheduledTime": {
                "utc": "2024-04-03 05:00Z",
                "local": "2024-04-03 12:00+07:00"
            }
        },
        "aircraft": {
            "model": "Boeing 737-800"
        },
        "airline": {
            "name": "Garuda Indonesia",
            "iata": "GA",
            "icao": "GIA"
        }
    },
    {
        "movement": {
            "airport": {
                "icao": "WIDD",
                "iata": "BTH",
                "name": "Batam Island",
                "timeZone": "Asia/Jakarta"
            },
            "scheduledTime": {
                "utc": "2024-04-03 05:15Z",
                "local": "2024-04-03 12:15+07:00"
            }
        },
        "aircraft": {
            "model": "Airbus A320"
        },
        "airline": {
            "name": "Citilink",
            "iata": "QG",
            "icao": "CTV"
        }
    },
    {
        "movement": {
            "airport": {
                "icao": "WIHH",
                "iata": "HLP",
                "name": "Jakarta",
                "timeZone": "Asia/Jakarta"
            },
            "scheduledTime": {
                "utc": "2024-04-03 06:10Z",
                "local": "2024-04-03 13:10+07:00"
            }
        },
        "aircraft": {
            "model": "Airbus A320"
        },
        "airline": {
            "name": "Citilink",
            "iata": "QG",
            "icao": "CTV"
        }
    },
    {
        "movement": {
            "airport": {
                "icao": "WIII",
                "iata": "CGK",
                "name": "Jakarta",
                "timeZone": "Asia/Jakarta"
            },
            "scheduledTime": {
                "utc": "2024-04-03 06:15Z",
                "local": "2024-04-03 13:15+07:00"
            }
        },
        "aircraft": {
            "model": "Airbus A320"
        },
        "airline": {
            "name": "Super Air Jet",
            "iata": "IU",
            "icao": "SJV"
        }
    },
    {
        "movement": {
            "airport": {
                "icao": "WIII",
                "iata": "CGK",
                "name": "Jakarta",
                "timeZone": "Asia/Jakarta"
            },
            "scheduledTime": {
                "utc": "2024-04-03 06:25Z",
                "local": "2024-04-03 13:25+07:00"
            }
        },
        "aircraft": {
            "model": "Airbus A320"
        },
        "airline": {
            "name": "Super Air Jet",
            "iata": "IU",
            "icao": "SJV"
        }
    },
    {
        "movement": {
            "airport": {
                "icao": "WMKK",
                "iata": "KUL",
                "name": "Kuala Lumpur",
                "timeZone": "Asia/Kuala_Lumpur"
            },
            "scheduledTime": {
                "utc": "2024-04-03 06:40Z",
                "local": "2024-04-03 13:40+07:00"
            }
        },
        "aircraft": {
            "model": "Airbus A320"
        },
        "airline": {
            "name": "Super Air Jet",
            "iata": "IU",
            "icao": "SJV"
        }
    },
    {
        "movement": {
            "airport": {
                "icao": "WIII",
                "iata": "CGK",
                "name": "Jakarta",
                "timeZone": "Asia/Jakarta"
            },
            "scheduledTime": {
                "utc": "2024-04-03 07:20Z",
                "local": "2024-04-03 14:20+07:00"
            }
        },
        "aircraft": {
            "model": "Airbus A320"
        },
        "airline": {
            "name": "Citilink",
            "iata": "QG",
            "icao": "CTV"
        }
    },
    {
        "movement": {
            "airport": {
                "icao": "WIII",
                "iata": "CGK",
                "name": "Jakarta",
                "timeZone": "Asia/Jakarta"
            },
            "scheduledTime": {
                "utc": "2024-04-03 08:00Z",
                "local": "2024-04-03 15:00+07:00"
            }
        },
        "aircraft": {
            "model": "Airbus A320"
        },
        "airline": {
            "name": "Super Air Jet",
            "iata": "IU",
            "icao": "SJV"
        }
    },
    {
        "movement": {
            "airport": {
                "icao": "WMKK",
                "iata": "KUL",
                "name": "Kuala Lumpur",
                "timeZone": "Asia/Kuala_Lumpur"
            },
            "scheduledTime": {
                "utc": "2024-04-03 09:05Z",
                "local": "2024-04-03 16:05+07:00"
            }
        },
        "aircraft": {
            "model": "Airbus A320"
        },
        "airline": {
            "name": "AirAsia",
            "iata": "AK",
            "icao": "AXM"
        }
    },
    {
        "movement": {
            "airport": {
                "icao": "WIDD",
                "iata": "BTH",
                "name": "Batam Island",
                "timeZone": "Asia/Jakarta"
            },
            "scheduledTime": {
                "utc": "2024-04-03 09:10Z",
                "local": "2024-04-03 16:10+07:00"
            }
        },
        "aircraft": {
            "model": "Boeing 737-900"
        },
        "airline": {
            "name": "Lion Air",
            "iata": "JT",
            "icao": "LNI"
        }
    },
    {
        "movement": {
            "airport": {
                "icao": "WIII",
                "iata": "CGK",
                "name": "Jakarta",
                "timeZone": "Asia/Jakarta"
            },
            "scheduledTime": {
                "utc": "2024-04-03 09:35Z",
                "local": "2024-04-03 16:35+07:00"
            }
        },
        "aircraft": {
            "model": "Airbus A320"
        },
        "airline": {
            "name": "Super Air Jet",
            "iata": "IU",
            "icao": "SJV"
        }
    },
    {
        "movement": {
            "airport": {
                "icao": "WIII",
                "iata": "CGK",
                "name": "Jakarta",
                "timeZone": "Asia/Jakarta"
            },
            "scheduledTime": {
                "utc": "2024-04-03 09:45Z",
                "local": "2024-04-03 16:45+07:00"
            }
        },
        "aircraft": {
            "model": "Airbus A330-900"
        },
        "airline": {
            "name": "Garuda Indonesia",
            "iata": "GA",
            "icao": "GIA"
        }
    },
    {
        "movement": {
            "airport": {
                "icao": "WIII",
                "iata": "CGK",
                "name": "Jakarta",
                "timeZone": "Asia/Jakarta"
            },
            "scheduledTime": {
                "utc": "2024-04-03 10:50Z",
                "local": "2024-04-03 17:50+07:00"
            }
        },
        "aircraft": {
            "model": "Airbus A320"
        },
        "airline": {
            "name": "Citilink",
            "iata": "QG",
            "icao": "CTV"
        }
    },
    {
        "movement": {
            "airport": {
                "icao": "WIII",
                "iata": "CGK",
                "name": "Jakarta",
                "timeZone": "Asia/Jakarta"
            },
            "scheduledTime": {
                "utc": "2024-04-03 11:30Z",
                "local": "2024-04-03 18:30+07:00"
            }
        },
        "aircraft": {
            "model": "Airbus A320"
        },
        "airline": {
            "name": "Super Air Jet",
            "iata": "IU",
            "icao": "SJV"
        }
    },
    {
        "movement": {
            "airport": {
                "icao": "WIHH",
                "iata": "HLP",
                "name": "Jakarta",
                "timeZone": "Asia/Jakarta"
            },
            "scheduledTime": {
                "utc": "2024-04-03 11:30Z",
                "local": "2024-04-03 18:30+07:00"
            }
        },
        "aircraft": {
            "model": "Airbus A320"
        },
        "airline": {
            "name": "Citilink",
            "iata": "QG",
            "icao": "CTV"
        }
    },
    {
        "movement": {
            "airport": {
                "icao": "WIII",
                "iata": "CGK",
                "name": "Jakarta",
                "timeZone": "Asia/Jakarta"
            },
            "scheduledTime": {
                "utc": "2024-04-03 12:10Z",
                "local": "2024-04-03 19:10+07:00"
            }
        },
        "aircraft": {
            "model": "Airbus A320"
        },
        "airline": {
            "name": "Citilink",
            "iata": "QG",
            "icao": "CTV"
        }
    },
    {
        "movement": {
            "airport": {
                "icao": "WIDD",
                "iata": "BTH",
                "name": "Batam Island",
                "timeZone": "Asia/Jakarta"
            },
            "scheduledTime": {
                "utc": "2024-04-03 12:15Z",
                "local": "2024-04-03 19:15+07:00"
            }
        },
        "aircraft": {
            "model": "Airbus A320"
        },
        "airline": {
            "name": "Citilink",
            "iata": "QG",
            "icao": "CTV"
        }
    },
    {
        "movement": {
            "airport": {
                "icao": "WIII",
                "iata": "CGK",
                "name": "Jakarta",
                "timeZone": "Asia/Jakarta"
            },
            "scheduledTime": {
                "utc": "2024-04-03 12:25Z",
                "local": "2024-04-03 19:25+07:00"
            }
        },
        "aircraft": {
            "model": "Airbus A320"
        },
        "airline": {
            "name": "Super Air Jet",
            "iata": "IU",
            "icao": "SJV"
        }
    },
    {
        "movement": {
            "airport": {
                "icao": "WIII",
                "iata": "CGK",
                "name": "Jakarta",
                "timeZone": "Asia/Jakarta"
            },
            "scheduledTime": {
                "utc": "2024-04-03 12:55Z",
                "local": "2024-04-03 19:55+07:00"
            }
        },
        "aircraft": {
            "model": "Airbus A320"
        },
        "airline": {
            "name": "Super Air Jet",
            "iata": "IU",
            "icao": "SJV"
        }
    },
    {
        "movement": {
            "airport": {
                "icao": "WIII",
                "iata": "CGK",
                "name": "Jakarta",
                "timeZone": "Asia/Jakarta"
            },
            "scheduledTime": {
                "utc": "2024-04-03 13:15Z",
                "local": "2024-04-03 20:15+07:00"
            }
        },
        "aircraft": {
            "model": "Airbus A320"
        },
        "airline": {
            "name": "Super Air Jet",
            "iata": "IU",
            "icao": "SJV"
        }
    },
    {
        "movement": {
            "airport": {
                "icao": "WIMM",
                "iata": "KNO",
                "name": "Medan",
                "timeZone": "Asia/Jakarta"
            },
            "scheduledTime": {
                "utc": "2024-04-04 00:00Z",
                "local": "2024-04-04 07:00+07:00"
            }
        },
        "aircraft": {
            "model": "Airbus A320"
        },
        "airline": {
            "name": "Super Air Jet",
            "iata": "IU",
            "icao": "SJV"
        }
    },
    {
        "movement": {
            "airport": {
                "icao": "WIDD",
                "iata": "BTH",
                "name": "Batam Island",
                "timeZone": "Asia/Jakarta"
            },
            "scheduledTime": {
                "utc": "2024-04-04 00:00Z",
                "local": "2024-04-04 07:00+07:00"
            }
        },
        "aircraft": {
            "model": "Airbus A320"
        },
        "airline": {
            "name": "Super Air Jet",
            "iata": "IU",
            "icao": "SJV"
        }
    },
    {
        "movement": {
            "airport": {
                "icao": "WIII",
                "iata": "CGK",
                "name": "Jakarta",
                "timeZone": "Asia/Jakarta"
            },
            "scheduledTime": {
                "utc": "2024-04-04 00:05Z",
                "local": "2024-04-04 07:05+07:00"
            }
        },
        "aircraft": {
            "model": "Airbus A320"
        },
        "airline": {
            "name": "Super Air Jet",
            "iata": "IU",
            "icao": "SJV"
        }
    },
    {
        "movement": {
            "airport": {
                "icao": "WIII",
                "iata": "CGK",
                "name": "Jakarta",
                "timeZone": "Asia/Jakarta"
            },
            "scheduledTime": {
                "utc": "2024-04-04 01:00Z",
                "local": "2024-04-04 08:00+07:00"
            }
        },
        "aircraft": {
            "model": "Boeing 737-800"
        },
        "airline": {
            "name": "Garuda Indonesia",
            "iata": "GA",
            "icao": "GIA"
        }
    },
    {
        "movement": {
            "airport": {
                "icao": "WMKK",
                "iata": "KUL",
                "name": "Kuala Lumpur",
                "timeZone": "Asia/Kuala_Lumpur"
            },
            "scheduledTime": {
                "utc": "2024-04-04 01:25Z",
                "local": "2024-04-04 08:25+07:00"
            }
        },
        "aircraft": {
            "model": "Airbus A320 NEO"
        },
        "airline": {
            "name": "AirAsia",
            "iata": "AK",
            "icao": "AXM"
        }
    },
    {
        "movement": {
            "airport": {
                "icao": "WIDD",
                "iata": "BTH",
                "name": "Batam Island",
                "timeZone": "Asia/Jakarta"
            },
            "scheduledTime": {
                "utc": "2024-04-04 01:55Z",
                "local": "2024-04-04 08:55+07:00"
            }
        },
        "aircraft": {
            "model": "Boeing 737-900"
        },
        "airline": {
            "name": "Lion Air",
            "iata": "JT",
            "icao": "LNI"
        }
    },
    {
        "movement": {
            "airport": {
                "icao": "WIDD",
                "iata": "BTH",
                "name": "Batam Island",
                "timeZone": "Asia/Jakarta"
            },
            "scheduledTime": {
                "utc": "2024-04-04 02:20Z",
                "local": "2024-04-04 09:20+07:00"
            }
        },
        "aircraft": {
            "model": "Airbus A320"
        },
        "airline": {
            "name": "Citilink",
            "iata": "QG",
            "icao": "CTV"
        }
    },
    {
        "movement": {
            "airport": {
                "icao": "WIII",
                "iata": "CGK",
                "name": "Jakarta",
                "timeZone": "Asia/Jakarta"
            },
            "scheduledTime": {
                "utc": "2024-04-04 02:25Z",
                "local": "2024-04-04 09:25+07:00"
            }
        },
        "aircraft": {
            "model": "Airbus A320"
        },
        "airline": {
            "name": "Citilink",
            "iata": "QG",
            "icao": "CTV"
        }
    },
    {
        "movement": {
            "airport": {
                "icao": "WIII",
                "iata": "CGK",
                "name": "Jakarta",
                "timeZone": "Asia/Jakarta"
            },
            "scheduledTime": {
                "utc": "2024-04-04 03:00Z",
                "local": "2024-04-04 10:00+07:00"
            }
        },
        "aircraft": {
            "model": "Airbus A320"
        },
        "airline": {
            "name": "Super Air Jet",
            "iata": "IU",
            "icao": "SJV"
        }
    },
    {
        "movement": {
            "airport": {
                "icao": "WIMM",
                "iata": "KNO",
                "name": "Medan",
                "timeZone": "Asia/Jakarta"
            },
            "scheduledTime": {
                "utc": "2024-04-04 03:20Z",
                "local": "2024-04-04 10:20+07:00"
            }
        },
        "aircraft": {
            "model": "Airbus A320"
        },
        "airline": {
            "name": "Super Air Jet",
            "iata": "IU",
            "icao": "SJV"
        }
    },
    {
        "movement": {
            "airport": {
                "icao": "WIDD",
                "iata": "BTH",
                "name": "Batam Island",
                "timeZone": "Asia/Jakarta"
            },
            "scheduledTime": {
                "utc": "2024-04-04 03:40Z",
                "local": "2024-04-04 10:40+07:00"
            }
        },
        "aircraft": {
            "model": "Airbus A320"
        },
        "airline": {
            "name": "Super Air Jet",
            "iata": "IU",
            "icao": "SJV"
        }
    },
    {
        "movement": {
            "airport": {
                "icao": "WIDD",
                "iata": "BTH",
                "name": "Batam Island",
                "timeZone": "Asia/Jakarta"
            },
            "scheduledTime": {
                "utc": "2024-04-04 04:30Z",
                "local": "2024-04-04 11:30+07:00"
            }
        },
        "aircraft": {
            "model": "Boeing 737-800"
        },
        "airline": {
            "name": "Lion Air",
            "iata": "JT",
            "icao": "LNI"
        }
    },
    {
        "movement": {
            "airport": {
                "icao": "WMKK",
                "iata": "KUL",
                "name": "Kuala Lumpur",
                "timeZone": "Asia/Kuala_Lumpur"
            },
            "scheduledTime": {
                "utc": "2024-04-04 04:35Z",
                "local": "2024-04-04 11:35+07:00"
            }
        },
        "aircraft": {
            "model": "Airbus A320"
        },
        "airline": {
            "name": "AirAsia",
            "iata": "AK",
            "icao": "AXM"
        }
    },
    {
        "movement": {
            "airport": {
                "icao": "WIII",
                "iata": "CGK",
                "name": "Jakarta",
                "timeZone": "Asia/Jakarta"
            },
            "scheduledTime": {
                "utc": "2024-04-04 05:00Z",
                "local": "2024-04-04 12:00+07:00"
            }
        },
        "aircraft": {
            "model": "Boeing 737-800"
        },
        "airline": {
            "name": "Garuda Indonesia",
            "iata": "GA",
            "icao": "GIA"
        }
    },
    {
        "movement": {
            "airport": {
                "icao": "WIHH",
                "iata": "HLP",
                "name": "Jakarta",
                "timeZone": "Asia/Jakarta"
            },
            "scheduledTime": {
                "utc": "2024-04-04 06:10Z",
                "local": "2024-04-04 13:10+07:00"
            }
        },
        "aircraft": {
            "model": "Airbus A320"
        },
        "airline": {
            "name": "Citilink",
            "iata": "QG",
            "icao": "CTV"
        }
    },
    {
        "movement": {
            "airport": {
                "icao": "WIII",
                "iata": "CGK",
                "name": "Jakarta",
                "timeZone": "Asia/Jakarta"
            },
            "scheduledTime": {
                "utc": "2024-04-04 06:15Z",
                "local": "2024-04-04 13:15+07:00"
            }
        },
        "aircraft": {
            "model": "Airbus A320"
        },
        "airline": {
            "name": "Super Air Jet",
            "iata": "IU",
            "icao": "SJV"
        }
    },
    {
        "movement": {
            "airport": {
                "icao": "WIII",
                "iata": "CGK",
                "name": "Jakarta",
                "timeZone": "Asia/Jakarta"
            },
            "scheduledTime": {
                "utc": "2024-04-04 06:25Z",
                "local": "2024-04-04 13:25+07:00"
            }
        },
        "aircraft": {
            "model": "Airbus A320"
        },
        "airline": {
            "name": "Super Air Jet",
            "iata": "IU",
            "icao": "SJV"
        }
    },
    {
        "movement": {
            "airport": {
                "icao": "WMKK",
                "iata": "KUL",
                "name": "Kuala Lumpur",
                "timeZone": "Asia/Kuala_Lumpur"
            },
            "scheduledTime": {
                "utc": "2024-04-04 06:40Z",
                "local": "2024-04-04 13:40+07:00"
            }
        },
        "aircraft": {
            "model": "Airbus A320"
        },
        "airline": {
            "name": "Super Air Jet",
            "iata": "IU",
            "icao": "SJV"
        }
    },
    {
        "movement": {
            "airport": {
                "icao": "WIII",
                "iata": "CGK",
                "name": "Jakarta",
                "timeZone": "Asia/Jakarta"
            },
            "scheduledTime": {
                "utc": "2024-04-04 07:20Z",
                "local": "2024-04-04 14:20+07:00"
            }
        },
        "aircraft": {
            "model": "Airbus A320"
        },
        "airline": {
            "name": "Citilink",
            "iata": "QG",
            "icao": "CTV"
        }
    },
    {
        "movement": {
            "airport": {
                "icao": "WIII",
                "iata": "CGK",
                "name": "Jakarta",
                "timeZone": "Asia/Jakarta"
            },
            "scheduledTime": {
                "utc": "2024-04-04 08:00Z",
                "local": "2024-04-04 15:00+07:00"
            }
        },
        "aircraft": {
            "model": "Airbus A320"
        },
        "airline": {
            "name": "Super Air Jet",
            "iata": "IU",
            "icao": "SJV"
        }
    },
    {
        "movement": {
            "airport": {
                "icao": "WIDD",
                "iata": "BTH",
                "name": "Batam Island",
                "timeZone": "Asia/Jakarta"
            },
            "scheduledTime": {
                "utc": "2024-04-04 09:10Z",
                "local": "2024-04-04 16:10+07:00"
            }
        },
        "aircraft": {
            "model": "Boeing 737-900"
        },
        "airline": {
            "name": "Lion Air",
            "iata": "JT",
            "icao": "LNI"
        }
    },
    {
        "movement": {
            "airport": {
                "icao": "WIII",
                "iata": "CGK",
                "name": "Jakarta",
                "timeZone": "Asia/Jakarta"
            },
            "scheduledTime": {
                "utc": "2024-04-04 09:30Z",
                "local": "2024-04-04 16:30+07:00"
            }
        },
        "aircraft": {
            "model": "Boeing 737-800"
        },
        "airline": {
            "name": "Garuda Indonesia",
            "iata": "GA",
            "icao": "GIA"
        }
    },
    {
        "movement": {
            "airport": {
                "icao": "WIII",
                "iata": "CGK",
                "name": "Jakarta",
                "timeZone": "Asia/Jakarta"
            },
            "scheduledTime": {
                "utc": "2024-04-04 09:35Z",
                "local": "2024-04-04 16:35+07:00"
            }
        },
        "aircraft": {
            "model": "Airbus A320"
        },
        "airline": {
            "name": "Super Air Jet",
            "iata": "IU",
            "icao": "SJV"
        }
    },
    {
        "movement": {
            "airport": {
                "icao": "WMKK",
                "iata": "KUL",
                "name": "Kuala Lumpur",
                "timeZone": "Asia/Kuala_Lumpur"
            },
            "scheduledTime": {
                "utc": "2024-04-04 10:20Z",
                "local": "2024-04-04 17:20+07:00"
            }
        },
        "aircraft": {
            "model": "Airbus A320"
        },
        "airline": {
            "name": "AirAsia",
            "iata": "AK",
            "icao": "AXM"
        }
    },
    {
        "movement": {
            "airport": {
                "icao": "WIII",
                "iata": "CGK",
                "name": "Jakarta",
                "timeZone": "Asia/Jakarta"
            },
            "scheduledTime": {
                "utc": "2024-04-04 10:50Z",
                "local": "2024-04-04 17:50+07:00"
            }
        },
        "aircraft": {
            "model": "Airbus A320"
        },
        "airline": {
            "name": "Citilink",
            "iata": "QG",
            "icao": "CTV"
        }
    },
    {
        "movement": {
            "airport": {
                "icao": "WIII",
                "iata": "CGK",
                "name": "Jakarta",
                "timeZone": "Asia/Jakarta"
            },
            "scheduledTime": {
                "utc": "2024-04-04 11:30Z",
                "local": "2024-04-04 18:30+07:00"
            }
        },
        "aircraft": {
            "model": "Airbus A320"
        },
        "airline": {
            "name": "Super Air Jet",
            "iata": "IU",
            "icao": "SJV"
        }
    },
    {
        "movement": {
            "airport": {
                "icao": "WIII",
                "iata": "CGK",
                "name": "Jakarta",
                "timeZone": "Asia/Jakarta"
            },
            "scheduledTime": {
                "utc": "2024-04-04 12:10Z",
                "local": "2024-04-04 19:10+07:00"
            }
        },
        "aircraft": {
            "model": "Airbus A320"
        },
        "airline": {
            "name": "Citilink",
            "iata": "QG",
            "icao": "CTV"
        }
    },
    {
        "movement": {
            "airport": {
                "icao": "WIDD",
                "iata": "BTH",
                "name": "Batam Island",
                "timeZone": "Asia/Jakarta"
            },
            "scheduledTime": {
                "utc": "2024-04-04 12:15Z",
                "local": "2024-04-04 19:15+07:00"
            }
        },
        "aircraft": {
            "model": "Airbus A320"
        },
        "airline": {
            "name": "Citilink",
            "iata": "QG",
            "icao": "CTV"
        }
    },
    {
        "movement": {
            "airport": {
                "icao": "WIII",
                "iata": "CGK",
                "name": "Jakarta",
                "timeZone": "Asia/Jakarta"
            },
            "scheduledTime": {
                "utc": "2024-04-04 12:25Z",
                "local": "2024-04-04 19:25+07:00"
            }
        },
        "aircraft": {
            "model": "Airbus A320"
        },
        "airline": {
            "name": "Super Air Jet",
            "iata": "IU",
            "icao": "SJV"
        }
    },
    {
        "movement": {
            "airport": {
                "icao": "WIII",
                "iata": "CGK",
                "name": "Jakarta",
                "timeZone": "Asia/Jakarta"
            },
            "scheduledTime": {
                "utc": "2024-04-04 12:55Z",
                "local": "2024-04-04 19:55+07:00"
            }
        },
        "aircraft": {
            "model": "Airbus A320"
        },
        "airline": {
            "name": "Super Air Jet",
            "iata": "IU",
            "icao": "SJV"
        }
    },
    {
        "movement": {
            "airport": {
                "icao": "WIII",
                "iata": "CGK",
                "name": "Jakarta",
                "timeZone": "Asia/Jakarta"
            },
            "scheduledTime": {
                "utc": "2024-04-04 13:15Z",
                "local": "2024-04-04 20:15+07:00"
            }
        },
        "aircraft": {
            "model": "Airbus A320"
        },
        "airline": {
            "name": "Super Air Jet",
            "iata": "IU",
            "icao": "SJV"
        }
    },
    {
        "movement": {
            "airport": {
                "icao": "WIII",
                "iata": "CGK",
                "name": "Jakarta",
                "timeZone": "Asia/Jakarta"
            },
            "scheduledTime": {
                "utc": "2024-04-04 14:30Z",
                "local": "2024-04-04 21:30+07:00"
            }
        },
        "aircraft": {
            "model": "Airbus A320"
        },
        "airline": {
            "name": "Super Air Jet",
            "iata": "IU",
            "icao": "SJV"
        }
    },
    {
        "movement": {
            "airport": {
                "icao": "WIII",
                "iata": "CGK",
                "name": "Jakarta",
                "timeZone": "Asia/Jakarta"
            },
            "scheduledTime": {
                "utc": "2024-04-04 14:50Z",
                "local": "2024-04-04 21:50+07:00"
            }
        },
        "aircraft": {
            "model": "Airbus A320"
        },
        "airline": {
            "name": "Super Air Jet",
            "iata": "IU",
            "icao": "SJV"
        }
    },
    {
        "movement": {
            "airport": {
                "icao": "WIII",
                "iata": "CGK",
                "name": "Jakarta",
                "timeZone": "Asia/Jakarta"
            },
            "scheduledTime": {
                "utc": "2024-04-05 01:00Z",
                "local": "2024-04-05 08:00+07:00"
            }
        },
        "aircraft": {
            "model": "Boeing 737-800"
        },
        "airline": {
            "name": "Garuda Indonesia",
            "iata": "GA",
            "icao": "GIA"
        }
    },
    {
        "movement": {
            "airport": {
                "icao": "WMKK",
                "iata": "KUL",
                "name": "Kuala Lumpur",
                "timeZone": "Asia/Kuala_Lumpur"
            },
            "scheduledTime": {
                "utc": "2024-04-05 01:25Z",
                "local": "2024-04-05 08:25+07:00"
            }
        },
        "aircraft": {
            "model": "Airbus A320"
        },
        "airline": {
            "name": "AirAsia",
            "iata": "AK",
            "icao": "AXM"
        }
    },
    {
        "movement": {
            "airport": {
                "icao": "WIDD",
                "iata": "BTH",
                "name": "Batam Island",
                "timeZone": "Asia/Jakarta"
            },
            "scheduledTime": {
                "utc": "2024-04-05 01:55Z",
                "local": "2024-04-05 08:55+07:00"
            }
        },
        "aircraft": {
            "model": "Boeing 737-900"
        },
        "airline": {
            "name": "Lion Air",
            "iata": "JT",
            "icao": "LNI"
        }
    },
    {
        "movement": {
            "airport": {
                "icao": "WIII",
                "iata": "CGK",
                "name": "Jakarta",
                "timeZone": "Asia/Jakarta"
            },
            "scheduledTime": {
                "utc": "2024-04-05 02:25Z",
                "local": "2024-04-05 09:25+07:00"
            }
        },
        "aircraft": {
            "model": "Airbus A320"
        },
        "airline": {
            "name": "Citilink",
            "iata": "QG",
            "icao": "CTV"
        }
    },
    {
        "movement": {
            "airport": {
                "icao": "WIII",
                "iata": "CGK",
                "name": "Jakarta",
                "timeZone": "Asia/Jakarta"
            },
            "scheduledTime": {
                "utc": "2024-04-05 03:00Z",
                "local": "2024-04-05 10:00+07:00"
            }
        },
        "aircraft": {
            "model": "Airbus A320"
        },
        "airline": {
            "name": "Super Air Jet",
            "iata": "IU",
            "icao": "SJV"
        }
    },
    {
        "movement": {
            "airport": {
                "icao": "WIMM",
                "iata": "KNO",
                "name": "Medan",
                "timeZone": "Asia/Jakarta"
            },
            "scheduledTime": {
                "utc": "2024-04-05 03:20Z",
                "local": "2024-04-05 10:20+07:00"
            }
        },
        "aircraft": {
            "model": "Airbus A320"
        },
        "airline": {
            "name": "Super Air Jet",
            "iata": "IU",
            "icao": "SJV"
        }
    },
    {
        "movement": {
            "airport": {
                "icao": "WIDD",
                "iata": "BTH",
                "name": "Batam Island",
                "timeZone": "Asia/Jakarta"
            },
            "scheduledTime": {
                "utc": "2024-04-05 03:40Z",
                "local": "2024-04-05 10:40+07:00"
            }
        },
        "aircraft": {
            "model": "Airbus A320"
        },
        "airline": {
            "name": "Super Air Jet",
            "iata": "IU",
            "icao": "SJV"
        }
    },
    {
        "movement": {
            "airport": {
                "icao": "WIII",
                "iata": "CGK",
                "name": "Jakarta",
                "timeZone": "Asia/Jakarta"
            },
            "scheduledTime": {
                "utc": "2024-04-05 00:05Z",
                "local": "2024-04-05 07:05+07:00"
            }
        },
        "aircraft": {
            "model": "Airbus A320"
        },
        "airline": {
            "name": "Super Air Jet",
            "iata": "IU",
            "icao": "SJV"
        }
    },
    {
        "movement": {
            "airport": {
                "icao": "WIDD",
                "iata": "BTH",
                "name": "Batam Island",
                "timeZone": "Asia/Jakarta"
            },
            "scheduledTime": {
                "utc": "2024-04-05 00:00Z",
                "local": "2024-04-05 07:00+07:00"
            }
        },
        "aircraft": {
            "model": "Airbus A320"
        },
        "airline": {
            "name": "Super Air Jet",
            "iata": "IU",
            "icao": "SJV"
        }
    },
    {
        "movement": {
            "airport": {
                "icao": "WIMM",
                "iata": "KNO",
                "name": "Medan",
                "timeZone": "Asia/Jakarta"
            },
            "scheduledTime": {
                "utc": "2024-04-05 00:00Z",
                "local": "2024-04-05 07:00+07:00"
            }
        },
        "aircraft": {
            "model": "Airbus A320"
        },
        "airline": {
            "name": "Super Air Jet",
            "iata": "IU",
            "icao": "SJV"
        }
    },
    {
        "movement": {
            "airport": {
                "icao": "WMKK",
                "iata": "KUL",
                "name": "Kuala Lumpur",
                "timeZone": "Asia/Kuala_Lumpur"
            },
            "scheduledTime": {
                "utc": "2024-04-05 04:35Z",
                "local": "2024-04-05 11:35+07:00"
            }
        },
        "aircraft": {
            "model": "Airbus A320"
        },
        "airline": {
            "name": "AirAsia",
            "iata": "AK",
            "icao": "AXM"
        }
    },
    {
        "movement": {
            "airport": {
                "icao": "WIDD",
                "iata": "BTH",
                "name": "Batam Island",
                "timeZone": "Asia/Jakarta"
            },
            "scheduledTime": {
                "utc": "2024-04-05 04:30Z",
                "local": "2024-04-05 11:30+07:00"
            }
        },
        "aircraft": {
            "model": "Boeing 737-800"
        },
        "airline": {
            "name": "Lion Air",
            "iata": "JT",
            "icao": "LNI"
        }
    },
    {
        "movement": {
            "airport": {
                "icao": "WIII",
                "iata": "CGK",
                "name": "Jakarta",
                "timeZone": "Asia/Jakarta"
            },
            "scheduledTime": {
                "utc": "2024-04-05 05:00Z",
                "local": "2024-04-05 12:00+07:00"
            }
        },
        "aircraft": {
            "model": "Boeing 737-800"
        },
        "airline": {
            "name": "Garuda Indonesia",
            "iata": "GA",
            "icao": "GIA"
        }
    },
    {
        "movement": {
            "airport": {
                "icao": "WIII",
                "iata": "CGK",
                "name": "Jakarta",
                "timeZone": "Asia/Jakarta"
            },
            "scheduledTime": {
                "utc": "2024-04-05 06:25Z",
                "local": "2024-04-05 13:25+07:00"
            }
        },
        "aircraft": {
            "model": "Airbus A320"
        },
        "airline": {
            "name": "Super Air Jet",
            "iata": "IU",
            "icao": "SJV"
        }
    },
    {
        "movement": {
            "airport": {
                "icao": "WMKK",
                "iata": "KUL",
                "name": "Kuala Lumpur",
                "timeZone": "Asia/Kuala_Lumpur"
            },
            "scheduledTime": {
                "utc": "2024-04-05 06:40Z",
                "local": "2024-04-05 13:40+07:00"
            }
        },
        "aircraft": {
            "model": "Airbus A320"
        },
        "airline": {
            "name": "Super Air Jet",
            "iata": "IU",
            "icao": "SJV"
        }
    },
    {
        "movement": {
            "airport": {
                "icao": "WIII",
                "iata": "CGK",
                "name": "Jakarta",
                "timeZone": "Asia/Jakarta"
            },
            "scheduledTime": {
                "utc": "2024-04-05 08:00Z",
                "local": "2024-04-05 15:00+07:00"
            }
        },
        "aircraft": {
            "model": "Airbus A320"
        },
        "airline": {
            "name": "Super Air Jet",
            "iata": "IU",
            "icao": "SJV"
        }
    },
    {
        "movement": {
            "airport": {
                "icao": "WMKK",
                "iata": "KUL",
                "name": "Kuala Lumpur",
                "timeZone": "Asia/Kuala_Lumpur"
            },
            "scheduledTime": {
                "utc": "2024-04-05 09:05Z",
                "local": "2024-04-05 16:05+07:00"
            }
        },
        "aircraft": {
            "model": "Airbus A320 NEO"
        },
        "airline": {
            "name": "AirAsia",
            "iata": "AK",
            "icao": "AXM"
        }
    },
    {
        "movement": {
            "airport": {
                "icao": "WIII",
                "iata": "CGK",
                "name": "Jakarta",
                "timeZone": "Asia/Jakarta"
            },
            "scheduledTime": {
                "utc": "2024-04-05 09:30Z",
                "local": "2024-04-05 16:30+07:00"
            }
        },
        "aircraft": {
            "model": "Boeing 737-800"
        },
        "airline": {
            "name": "Garuda Indonesia",
            "iata": "GA",
            "icao": "GIA"
        }
    },
    {
        "movement": {
            "airport": {
                "icao": "WIII",
                "iata": "CGK",
                "name": "Jakarta",
                "timeZone": "Asia/Jakarta"
            },
            "scheduledTime": {
                "utc": "2024-04-05 10:50Z",
                "local": "2024-04-05 17:50+07:00"
            }
        },
        "aircraft": {
            "model": "Airbus A320"
        },
        "airline": {
            "name": "Citilink",
            "iata": "QG",
            "icao": "CTV"
        }
    },
    {
        "movement": {
            "airport": {
                "icao": "WIII",
                "iata": "CGK",
                "name": "Jakarta",
                "timeZone": "Asia/Jakarta"
            },
            "scheduledTime": {
                "utc": "2024-04-05 11:30Z",
                "local": "2024-04-05 18:30+07:00"
            }
        },
        "aircraft": {
            "model": "Airbus A320"
        },
        "airline": {
            "name": "Super Air Jet",
            "iata": "IU",
            "icao": "SJV"
        }
    },
    {
        "movement": {
            "airport": {
                "icao": "WIII",
                "iata": "CGK",
                "name": "Jakarta",
                "timeZone": "Asia/Jakarta"
            },
            "scheduledTime": {
                "utc": "2024-04-05 12:10Z",
                "local": "2024-04-05 19:10+07:00"
            }
        },
        "aircraft": {
            "model": "Airbus A320"
        },
        "airline": {
            "name": "Citilink",
            "iata": "QG",
            "icao": "CTV"
        }
    },
    {
        "movement": {
            "airport": {
                "icao": "WIDD",
                "iata": "BTH",
                "name": "Batam Island",
                "timeZone": "Asia/Jakarta"
            },
            "scheduledTime": {
                "utc": "2024-04-05 12:15Z",
                "local": "2024-04-05 19:15+07:00"
            }
        },
        "aircraft": {
            "model": "Airbus A320"
        },
        "airline": {
            "name": "Citilink",
            "iata": "QG",
            "icao": "CTV"
        }
    },
    {
        "movement": {
            "airport": {
                "icao": "WIII",
                "iata": "CGK",
                "name": "Jakarta",
                "timeZone": "Asia/Jakarta"
            },
            "scheduledTime": {
                "utc": "2024-04-05 12:25Z",
                "local": "2024-04-05 19:25+07:00"
            }
        },
        "aircraft": {
            "model": "Airbus A320"
        },
        "airline": {
            "name": "Super Air Jet",
            "iata": "IU",
            "icao": "SJV"
        }
    },
    {
        "movement": {
            "airport": {
                "icao": "WIII",
                "iata": "CGK",
                "name": "Jakarta",
                "timeZone": "Asia/Jakarta"
            },
            "scheduledTime": {
                "utc": "2024-04-05 12:55Z",
                "local": "2024-04-05 19:55+07:00"
            }
        },
        "aircraft": {
            "model": "Airbus A320"
        },
        "airline": {
            "name": "Super Air Jet",
            "iata": "IU",
            "icao": "SJV"
        }
    },
    {
        "movement": {
            "airport": {
                "icao": "WIII",
                "iata": "CGK",
                "name": "Jakarta",
                "timeZone": "Asia/Jakarta"
            },
            "scheduledTime": {
                "utc": "2024-04-05 13:15Z",
                "local": "2024-04-05 20:15+07:00"
            }
        },
        "aircraft": {
            "model": "Airbus A320"
        },
        "airline": {
            "name": "Super Air Jet",
            "iata": "IU",
            "icao": "SJV"
        }
    },
    {
        "movement": {
            "airport": {
                "icao": "WIII",
                "iata": "CGK",
                "name": "Jakarta",
                "timeZone": "Asia/Jakarta"
            },
            "scheduledTime": {
                "utc": "2024-04-05 14:30Z",
                "local": "2024-04-05 21:30+07:00"
            }
        },
        "aircraft": {
            "model": "Airbus A320"
        },
        "airline": {
            "name": "Super Air Jet",
            "iata": "IU",
            "icao": "SJV"
        }
    },
    {
        "movement": {
            "airport": {
                "icao": "WIII",
                "iata": "CGK",
                "name": "Jakarta",
                "timeZone": "Asia/Jakarta"
            },
            "scheduledTime": {
                "utc": "2024-04-05 14:50Z",
                "local": "2024-04-05 21:50+07:00"
            }
        },
        "aircraft": {
            "model": "Airbus A320"
        },
        "airline": {
            "name": "Super Air Jet",
            "iata": "IU",
            "icao": "SJV"
        }
    },
    {
        "movement": {
            "airport": {
                "icao": "WIDD",
                "iata": "BTH",
                "name": "Batam Island",
                "timeZone": "Asia/Jakarta"
            },
            "scheduledTime": {
                "utc": "2024-04-05 09:10Z",
                "local": "2024-04-05 16:10+07:00"
            }
        },
        "aircraft": {
            "model": "Boeing 737-900"
        },
        "airline": {
            "name": "Lion Air",
            "iata": "JT",
            "icao": "LNI"
        }
    },
    {
        "movement": {
            "airport": {
                "icao": "WIII",
                "iata": "CGK",
                "name": "Jakarta",
                "timeZone": "Asia/Jakarta"
            },
            "scheduledTime": {
                "utc": "2024-04-05 09:35Z",
                "local": "2024-04-05 16:35+07:00"
            }
        },
        "aircraft": {
            "model": "Airbus A320"
        },
        "airline": {
            "name": "Super Air Jet",
            "iata": "IU",
            "icao": "SJV"
        }
    },
    {
        "movement": {
            "airport": {
                "icao": "WIHH",
                "iata": "HLP",
                "name": "Jakarta",
                "timeZone": "Asia/Jakarta"
            },
            "scheduledTime": {
                "utc": "2024-04-05 06:10Z",
                "local": "2024-04-05 13:10+07:00"
            }
        },
        "aircraft": {
            "model": "Airbus A320"
        },
        "airline": {
            "name": "Citilink",
            "iata": "QG",
            "icao": "CTV"
        }
    },
    {
        "movement": {
            "airport": {
                "icao": "WIII",
                "iata": "CGK",
                "name": "Jakarta",
                "timeZone": "Asia/Jakarta"
            },
            "scheduledTime": {
                "utc": "2024-04-05 06:15Z",
                "local": "2024-04-05 13:15+07:00"
            }
        },
        "aircraft": {
            "model": "Airbus A320"
        },
        "airline": {
            "name": "Super Air Jet",
            "iata": "IU",
            "icao": "SJV"
        }
    },
    {
        "movement": {
            "airport": {
                "icao": "WIII",
                "iata": "CGK",
                "name": "Jakarta",
                "timeZone": "Asia/Jakarta"
            },
            "scheduledTime": {
                "utc": "2024-04-05 07:20Z",
                "local": "2024-04-05 14:20+07:00"
            }
        },
        "aircraft": {
            "model": "Airbus A320"
        },
        "airline": {
            "name": "Citilink",
            "iata": "QG",
            "icao": "CTV"
        }
    },
    {
        "movement": {
            "airport": {
                "icao": "WIDD",
                "iata": "BTH",
                "name": "Batam Island",
                "timeZone": "Asia/Jakarta"
            },
            "scheduledTime": {
                "utc": "2024-04-06 01:55Z",
                "local": "2024-04-06 08:55+07:00"
            }
        },
        "aircraft": {
            "model": "Boeing 737-900"
        },
        "airline": {
            "name": "Lion Air",
            "iata": "JT",
            "icao": "LNI"
        }
    },
    {
        "movement": {
            "airport": {
                "icao": "WIII",
                "iata": "CGK",
                "name": "Jakarta",
                "timeZone": "Asia/Jakarta"
            },
            "scheduledTime": {
                "utc": "2024-04-06 02:25Z",
                "local": "2024-04-06 09:25+07:00"
            }
        },
        "aircraft": {
            "model": "Airbus A320"
        },
        "airline": {
            "name": "Citilink",
            "iata": "QG",
            "icao": "CTV"
        }
    },
    {
        "movement": {
            "airport": {
                "icao": "WIII",
                "iata": "CGK",
                "name": "Jakarta",
                "timeZone": "Asia/Jakarta"
            },
            "scheduledTime": {
                "utc": "2024-04-06 03:00Z",
                "local": "2024-04-06 10:00+07:00"
            }
        },
        "aircraft": {
            "model": "Airbus A320"
        },
        "airline": {
            "name": "Super Air Jet",
            "iata": "IU",
            "icao": "SJV"
        }
    },
    {
        "movement": {
            "airport": {
                "icao": "WIMM",
                "iata": "KNO",
                "name": "Medan",
                "timeZone": "Asia/Jakarta"
            },
            "scheduledTime": {
                "utc": "2024-04-06 03:20Z",
                "local": "2024-04-06 10:20+07:00"
            }
        },
        "aircraft": {
            "model": "Airbus A320"
        },
        "airline": {
            "name": "Super Air Jet",
            "iata": "IU",
            "icao": "SJV"
        }
    },
    {
        "movement": {
            "airport": {
                "icao": "WIDD",
                "iata": "BTH",
                "name": "Batam Island",
                "timeZone": "Asia/Jakarta"
            },
            "scheduledTime": {
                "utc": "2024-04-06 03:40Z",
                "local": "2024-04-06 10:40+07:00"
            }
        },
        "aircraft": {
            "model": "Airbus A320"
        },
        "airline": {
            "name": "Super Air Jet",
            "iata": "IU",
            "icao": "SJV"
        }
    },
    {
        "movement": {
            "airport": {
                "icao": "WIDD",
                "iata": "BTH",
                "name": "Batam Island",
                "timeZone": "Asia/Jakarta"
            },
            "scheduledTime": {
                "utc": "2024-04-06 04:30Z",
                "local": "2024-04-06 11:30+07:00"
            }
        },
        "aircraft": {
            "model": "Boeing 737-900"
        },
        "airline": {
            "name": "Lion Air",
            "iata": "JT",
            "icao": "LNI"
        }
    },
    {
        "movement": {
            "airport": {
                "icao": "WMKK",
                "iata": "KUL",
                "name": "Kuala Lumpur",
                "timeZone": "Asia/Kuala_Lumpur"
            },
            "scheduledTime": {
                "utc": "2024-04-06 04:35Z",
                "local": "2024-04-06 11:35+07:00"
            }
        },
        "aircraft": {
            "model": "Airbus A320"
        },
        "airline": {
            "name": "AirAsia",
            "iata": "AK",
            "icao": "AXM"
        }
    },
    {
        "movement": {
            "airport": {
                "icao": "WIDD",
                "iata": "BTH",
                "name": "Batam Island",
                "timeZone": "Asia/Jakarta"
            },
            "scheduledTime": {
                "utc": "2024-04-06 02:20Z",
                "local": "2024-04-06 09:20+07:00"
            }
        },
        "aircraft": {
            "model": "Airbus A320"
        },
        "airline": {
            "name": "Citilink",
            "iata": "QG",
            "icao": "CTV"
        }
    },
    {
        "movement": {
            "airport": {
                "icao": "WMKK",
                "iata": "KUL",
                "name": "Kuala Lumpur",
                "timeZone": "Asia/Kuala_Lumpur"
            },
            "scheduledTime": {
                "utc": "2024-04-06 01:25Z",
                "local": "2024-04-06 08:25+07:00"
            }
        },
        "aircraft": {
            "model": "Airbus A320 NEO"
        },
        "airline": {
            "name": "AirAsia",
            "iata": "AK",
            "icao": "AXM"
        }
    },
    {
        "movement": {
            "airport": {
                "icao": "WIII",
                "iata": "CGK",
                "name": "Jakarta",
                "timeZone": "Asia/Jakarta"
            },
            "scheduledTime": {
                "utc": "2024-04-06 01:00Z",
                "local": "2024-04-06 08:00+07:00"
            }
        },
        "aircraft": {
            "model": "Boeing 737-800"
        },
        "airline": {
            "name": "Garuda Indonesia",
            "iata": "GA",
            "icao": "GIA"
        }
    },
    {
        "movement": {
            "airport": {
                "icao": "WIII",
                "iata": "CGK",
                "name": "Jakarta",
                "timeZone": "Asia/Jakarta"
            },
            "scheduledTime": {
                "utc": "2024-04-06 00:05Z",
                "local": "2024-04-06 07:05+07:00"
            }
        },
        "aircraft": {
            "model": "Airbus A320"
        },
        "airline": {
            "name": "Super Air Jet",
            "iata": "IU",
            "icao": "SJV"
        }
    },
    {
        "movement": {
            "airport": {
                "icao": "WIDD",
                "iata": "BTH",
                "name": "Batam Island",
                "timeZone": "Asia/Jakarta"
            },
            "scheduledTime": {
                "utc": "2024-04-06 00:00Z",
                "local": "2024-04-06 07:00+07:00"
            }
        },
        "aircraft": {
            "model": "Airbus A320"
        },
        "airline": {
            "name": "Super Air Jet",
            "iata": "IU",
            "icao": "SJV"
        }
    },
    {
        "movement": {
            "airport": {
                "icao": "WIMM",
                "iata": "KNO",
                "name": "Medan",
                "timeZone": "Asia/Jakarta"
            },
            "scheduledTime": {
                "utc": "2024-04-06 00:00Z",
                "local": "2024-04-06 07:00+07:00"
            }
        },
        "aircraft": {
            "model": "Airbus A320"
        },
        "airline": {
            "name": "Super Air Jet",
            "iata": "IU",
            "icao": "SJV"
        }
    },
    {
        "movement": {
            "airport": {
                "icao": "WIII",
                "iata": "CGK",
                "name": "Jakarta",
                "timeZone": "Asia/Jakarta"
            },
            "scheduledTime": {
                "utc": "2024-04-06 05:00Z",
                "local": "2024-04-06 12:00+07:00"
            }
        },
        "aircraft": {
            "model": "Boeing 737-800"
        },
        "airline": {
            "name": "Garuda Indonesia",
            "iata": "GA",
            "icao": "GIA"
        }
    },
    {
        "movement": {
            "airport": {
                "icao": "WIII",
                "iata": "CGK",
                "name": "Jakarta",
                "timeZone": "Asia/Jakarta"
            },
            "scheduledTime": {
                "utc": "2024-04-06 06:25Z",
                "local": "2024-04-06 13:25+07:00"
            }
        },
        "aircraft": {
            "model": "Airbus A320"
        },
        "airline": {
            "name": "Super Air Jet",
            "iata": "IU",
            "icao": "SJV"
        }
    },
    {
        "movement": {
            "airport": {
                "icao": "WMKK",
                "iata": "KUL",
                "name": "Kuala Lumpur",
                "timeZone": "Asia/Kuala_Lumpur"
            },
            "scheduledTime": {
                "utc": "2024-04-06 06:40Z",
                "local": "2024-04-06 13:40+07:00"
            }
        },
        "aircraft": {
            "model": "Airbus A320"
        },
        "airline": {
            "name": "Super Air Jet",
            "iata": "IU",
            "icao": "SJV"
        }
    },
    {
        "movement": {
            "airport": {
                "icao": "WIII",
                "iata": "CGK",
                "name": "Jakarta",
                "timeZone": "Asia/Jakarta"
            },
            "scheduledTime": {
                "utc": "2024-04-06 07:20Z",
                "local": "2024-04-06 14:20+07:00"
            }
        },
        "aircraft": {
            "model": "Airbus A320"
        },
        "airline": {
            "name": "Citilink",
            "iata": "QG",
            "icao": "CTV"
        }
    },
    {
        "movement": {
            "airport": {
                "icao": "WIII",
                "iata": "CGK",
                "name": "Jakarta",
                "timeZone": "Asia/Jakarta"
            },
            "scheduledTime": {
                "utc": "2024-04-06 08:00Z",
                "local": "2024-04-06 15:00+07:00"
            }
        },
        "aircraft": {
            "model": "Airbus A320"
        },
        "airline": {
            "name": "Super Air Jet",
            "iata": "IU",
            "icao": "SJV"
        }
    },
    {
        "movement": {
            "airport": {
                "icao": "WIII",
                "iata": "CGK",
                "name": "Jakarta",
                "timeZone": "Asia/Jakarta"
            },
            "scheduledTime": {
                "utc": "2024-04-06 09:30Z",
                "local": "2024-04-06 16:30+07:00"
            }
        },
        "aircraft": {
            "model": "Boeing 737-800"
        },
        "airline": {
            "name": "Garuda Indonesia",
            "iata": "GA",
            "icao": "GIA"
        }
    },
    {
        "movement": {
            "airport": {
                "icao": "WIII",
                "iata": "CGK",
                "name": "Jakarta",
                "timeZone": "Asia/Jakarta"
            },
            "scheduledTime": {
                "utc": "2024-04-06 09:35Z",
                "local": "2024-04-06 16:35+07:00"
            }
        },
        "aircraft": {
            "model": "Airbus A320"
        },
        "airline": {
            "name": "Super Air Jet",
            "iata": "IU",
            "icao": "SJV"
        }
    },
    {
        "movement": {
            "airport": {
                "icao": "WIII",
                "iata": "CGK",
                "name": "Jakarta",
                "timeZone": "Asia/Jakarta"
            },
            "scheduledTime": {
                "utc": "2024-04-06 10:50Z",
                "local": "2024-04-06 17:50+07:00"
            }
        },
        "aircraft": {
            "model": "Airbus A320"
        },
        "airline": {
            "name": "Citilink",
            "iata": "QG",
            "icao": "CTV"
        }
    },
    {
        "movement": {
            "airport": {
                "icao": "WIII",
                "iata": "CGK",
                "name": "Jakarta",
                "timeZone": "Asia/Jakarta"
            },
            "scheduledTime": {
                "utc": "2024-04-06 11:30Z",
                "local": "2024-04-06 18:30+07:00"
            }
        },
        "aircraft": {
            "model": "Airbus A320"
        },
        "airline": {
            "name": "Super Air Jet",
            "iata": "IU",
            "icao": "SJV"
        }
    },
    {
        "movement": {
            "airport": {
                "icao": "WIDD",
                "iata": "BTH",
                "name": "Batam Island",
                "timeZone": "Asia/Jakarta"
            },
            "scheduledTime": {
                "utc": "2024-04-06 12:15Z",
                "local": "2024-04-06 19:15+07:00"
            }
        },
        "aircraft": {
            "model": "Airbus A320"
        },
        "airline": {
            "name": "Citilink",
            "iata": "QG",
            "icao": "CTV"
        }
    },
    {
        "movement": {
            "airport": {
                "icao": "WIII",
                "iata": "CGK",
                "name": "Jakarta",
                "timeZone": "Asia/Jakarta"
            },
            "scheduledTime": {
                "utc": "2024-04-06 12:25Z",
                "local": "2024-04-06 19:25+07:00"
            }
        },
        "aircraft": {
            "model": "Airbus A320"
        },
        "airline": {
            "name": "Super Air Jet",
            "iata": "IU",
            "icao": "SJV"
        }
    },
    {
        "movement": {
            "airport": {
                "icao": "WIII",
                "iata": "CGK",
                "name": "Jakarta",
                "timeZone": "Asia/Jakarta"
            },
            "scheduledTime": {
                "utc": "2024-04-06 12:55Z",
                "local": "2024-04-06 19:55+07:00"
            }
        },
        "aircraft": {
            "model": "Airbus A320"
        },
        "airline": {
            "name": "Super Air Jet",
            "iata": "IU",
            "icao": "SJV"
        }
    },
    {
        "movement": {
            "airport": {
                "icao": "WIDD",
                "iata": "BTH",
                "name": "Batam Island",
                "timeZone": "Asia/Jakarta"
            },
            "scheduledTime": {
                "utc": "2024-04-06 12:55Z",
                "local": "2024-04-06 19:55+07:00"
            }
        },
        "aircraft": {
            "model": "Boeing 737-900"
        },
        "airline": {
            "name": "Lion Air",
            "iata": "JT",
            "icao": "LNI"
        }
    },
    {
        "movement": {
            "airport": {
                "icao": "WIII",
                "iata": "CGK",
                "name": "Jakarta",
                "timeZone": "Asia/Jakarta"
            },
            "scheduledTime": {
                "utc": "2024-04-06 13:15Z",
                "local": "2024-04-06 20:15+07:00"
            }
        },
        "aircraft": {
            "model": "Airbus A320"
        },
        "airline": {
            "name": "Super Air Jet",
            "iata": "IU",
            "icao": "SJV"
        }
    },
    {
        "movement": {
            "airport": {
                "icao": "WIII",
                "iata": "CGK",
                "name": "Jakarta",
                "timeZone": "Asia/Jakarta"
            },
            "scheduledTime": {
                "utc": "2024-04-06 14:30Z",
                "local": "2024-04-06 21:30+07:00"
            }
        },
        "aircraft": {
            "model": "Airbus A320"
        },
        "airline": {
            "name": "Super Air Jet",
            "iata": "IU",
            "icao": "SJV"
        }
    },
    {
        "movement": {
            "airport": {
                "icao": "WIII",
                "iata": "CGK",
                "name": "Jakarta",
                "timeZone": "Asia/Jakarta"
            },
            "scheduledTime": {
                "utc": "2024-04-06 14:50Z",
                "local": "2024-04-06 21:50+07:00"
            }
        },
        "aircraft": {
            "model": "Airbus A320"
        },
        "airline": {
            "name": "Super Air Jet",
            "iata": "IU",
            "icao": "SJV"
        }
    },
    {
        "movement": {
            "airport": {
                "icao": "WIHH",
                "iata": "HLP",
                "name": "Jakarta",
                "timeZone": "Asia/Jakarta"
            },
            "scheduledTime": {
                "utc": "2024-04-06 06:10Z",
                "local": "2024-04-06 13:10+07:00"
            }
        },
        "aircraft": {
            "model": "Airbus A320"
        },
        "airline": {
            "name": "Citilink",
            "iata": "QG",
            "icao": "CTV"
        }
    },
    {
        "movement": {
            "airport": {
                "icao": "WIII",
                "iata": "CGK",
                "name": "Jakarta",
                "timeZone": "Asia/Jakarta"
            },
            "scheduledTime": {
                "utc": "2024-04-06 06:15Z",
                "local": "2024-04-06 13:15+07:00"
            }
        },
        "aircraft": {
            "model": "Airbus A320"
        },
        "airline": {
            "name": "Super Air Jet",
            "iata": "IU",
            "icao": "SJV"
        }
    },
    {
        "movement": {
            "airport": {
                "icao": "WIDD",
                "iata": "BTH",
                "name": "Batam Island",
                "timeZone": "Asia/Jakarta"
            },
            "scheduledTime": {
                "utc": "2024-04-06 09:10Z",
                "local": "2024-04-06 16:10+07:00"
            }
        },
        "aircraft": {
            "model": "Boeing 737-900"
        },
        "airline": {
            "name": "Lion Air",
            "iata": "JT",
            "icao": "LNI"
        }
    },
    {
        "movement": {
            "airport": {
                "icao": "WIMM",
                "iata": "KNO",
                "name": "Medan",
                "timeZone": "Asia/Jakarta"
            },
            "scheduledTime": {
                "utc": "2024-04-06 09:25Z",
                "local": "2024-04-06 16:25+07:00"
            }
        },
        "aircraft": {
            "model": "Airbus A320"
        },
        "airline": {
            "name": "Super Air Jet",
            "iata": "IU",
            "icao": "SJV"
        }
    },
    {
        "movement": {
            "airport": {
                "icao": "WIII",
                "iata": "CGK",
                "name": "Jakarta",
                "timeZone": "Asia/Jakarta"
            },
            "scheduledTime": {
                "utc": "2024-04-06 12:10Z",
                "local": "2024-04-06 19:10+07:00"
            }
        },
        "aircraft": {
            "model": "Airbus A320"
        },
        "airline": {
            "name": "Citilink",
            "iata": "QG",
            "icao": "CTV"
        }
    }
]