{"icao":"AGGN","iata":"GZO","shortName":"Nusatupe","fullName":"Gizo Nusatupe","municipalityName":"Gizo","location":{"lat":-8.09778,"lon":156.864},"elevation":{"meter":3.96,"km":0.0,"mile":0.0,"nm":0.0,"feet":13.0},"country":{"code":"SB","name":"Solomon Islands"},"continent":{"code":"OC","name":"Australia & Oceania"},"timeZone":"Pacific/Guadalcanal","urls":{"wikipedia":"https://en.wikipedia.org/wiki/Nusatupe_Airport","googleMaps":"https://www.google.com/maps/@-8.097780,156.863998,14z","flightRadar":"https://www.flightradar24.com/-8.10,156.86/14"}}