{"icao":"YBWW","iata":"WTB","shortName":"Brisbane West","fullName":"Wellcamp Brisbane West","municipalityName":"Wellcamp","location":{"lat":-27.558332,"lon":151.79333},"elevation":{"meter":459.94,"km":0.46,"mile":0.29,"nm":0.25,"feet":1509.0},"country":{"code":"AU","name":"Australia"},"continent":{"code":"OC","name":"Australia & Oceania"},"timeZone":"Australia/Brisbane","urls":{"webSite":"http://www.wellcamp.com.au","wikipedia":"https://en.wikipedia.org/wiki/Brisbane_West_Wellcamp_Airport","googleMaps":"https://www.google.com/maps/@-27.558333,151.793333,14z","flightRadar":"https://www.flightradar24.com/-27.56,151.79/14"}}